LICENSE
MANIFEST.in
README.md
process_image.py
pyproject.toml
setup.cfg
brainbow.egg-info/PKG-INFO
brainbow.egg-info/SOURCES.txt
brainbow.egg-info/dependency_links.txt
brainbow.egg-info/entry_points.txt
brainbow.egg-info/requires.txt
brainbow.egg-info/top_level.txt
src/colormaps.py
src/data_load.py
src/nipy.py
src/utils.py
src/data/__init__.py
src/data/mni_template.nii.gz
brainbow-0.1.11.dist-info/LICENSE
brainbow-0.1.11.dist-info/METADATA
brainbow-0.1.11.dist-info/WHEEL
brainbow-0.1.11.dist-info/entry_points.txt
brainbow-0.1.11.dist-info/top_level.txt
brainbow-0.1.11.dist-info/RECORD
