Metadata-Version: 2.1
Name: brainbow
Version: 0.1.11
Summary: Script for visualizing ICA/ROI brain parcellation
Author-email: Pavel Popov <paavali.popov@gmail.com>, Sergey Plis <s.m.plis@gmail.com>
Project-URL: Homepage, https://github.com/neuroneural/brainbow
Project-URL: Bug Tracker, https://github.com/neuroneural/brainbow/issues
Classifier: Programming Language :: Python :: 3
Classifier: License :: OSI Approved :: MIT License
Classifier: Operating System :: OS Independent
Requires-Python: >=3.6
License-File: LICENSE
Requires-Dist: numpy
Requires-Dist: matplotlib
Requires-Dist: nibabel
Requires-Dist: scipy
Requires-Dist: tqdm
Requires-Dist: importlib-resources
